plan_gui/__init__.py
plan_gui/plan_gui.py
plan_gui/gan_model/__init__.py
plan_gui/gan_model/attention_module.py
plan_gui/gan_model/generator.py
plan_gui/naive_bayes_model/__init__.py
pyctm/__init__.py
pyctm/codelet/__init__.py
pyctm/codelet/codelet.py
pyctm/codelet/codelet_application.py
pyctm/correction_engines/__init__.py
pyctm/correction_engines/naive_bayes_correction_engine.py
pyctm/memory/__init__.py
pyctm/memory/distributed_memory_type.py
pyctm/memory/k_distributed_memory.py
pyctm/memory/memory.py
pyctm/memory/memory_object.py
pyctm/memory/kafka/__init__.py
pyctm/memory/kafka/k_distributed_memory_behavior.py
pyctm/memory/kafka/topic_config_provider.py
pyctm/memory/kafka/builder/__init__.py
pyctm/memory/kafka/builder/k_consumer_builder.py
pyctm/memory/kafka/builder/k_producer_builder.py
pyctm/memory/kafka/config/__init__.py
pyctm/memory/kafka/config/topic_config.py
pyctm/memory/kafka/thread/__init__.py
pyctm/memory/kafka/thread/k_memory_content_publisher_thread.py
pyctm/memory/kafka/thread/k_memory_content_receiver_thread.py
pyctm/plan_gui/__init__.py
pyctm/plan_gui/plan_gui.py
pyctm/representation/__init__.py
pyctm/representation/array_dictionary.py
pyctm/representation/array_value_converter.py
pyctm/representation/array_value_validation.py
pyctm/representation/dictionary.py
pyctm/representation/idea.py
pyctm/representation/idea_metadata_values.py
pyctm/representation/sdr_idea.py
pyctm/representation/sdr_idea_array.py
pyctm/representation/sdr_idea_array_builder.py
pyctm/representation/sdr_idea_array_deserializer.py
pyctm/representation/sdr_idea_array_serializer.py
pyctm/representation/sdr_idea_builder.py
pyctm/representation/sdr_idea_deserializer.py
pyctm/representation/sdr_idea_serializer.py
pyctm/representation/value_converter.py
pyctm/representation/value_validation.py
pyctm/tests/__init__.py
pyctm/tests/k_distributed_memory_test.py
pyctm/tests/memory_object_test.py
pyctm/tests/sdr_idea_array_serializer_test.py
pyctm/tests/sdr_idea_serializer_test.py
pyctm-0.0.13.dist-info/LICENSE
pyctm-0.0.13.dist-info/METADATA
pyctm-0.0.13.dist-info/WHEEL
pyctm-0.0.13.dist-info/top_level.txt
pyctm-0.0.13.dist-info/RECORD
