Metadata-Version: 2.1
Name: pyctm
Version: 0.0.13
Summary: Python Cognitive System Toolkit for Microservices
Home-page: UNKNOWN
Author: Eduardo de Moraes Froes
License: MIT
Keywords: python,cst
Platform: UNKNOWN
License-File: LICENSE
Requires-Dist: confluent-kafka
Requires-Dist: matplotlib
Requires-Dist: numpy
Requires-Dist: scikit-learn
Requires-Dist: tk
Requires-Dist: torch
